setup.cfg
setup.py
python_jarvis/__init__.py
python_jarvis/helper_functions.py
python_jarvis.egg-info/PKG-INFO
python_jarvis.egg-info/SOURCES.txt
python_jarvis.egg-info/dependency_links.txt
python_jarvis.egg-info/top_level.txt