Metadata-Version: 1.1
Name: python-jarvis
Version: 0.1
Summary: Simple helper functions for python projects
Home-page: https://github.com/akash1551/python_jarvis.git
Author: Akash Wankhede
Author-email: acwankhede@gmail.com
License: UNKNOWN
Download-URL: https://github.com/akash1551/python_jarvis/archive/master.zip
Keywords: python helper functions,quicktool,regular used functions
Platform: UNKNOWN
Classifier: Development Status :: 4 - Beta
Classifier: Intended Audience :: System Administrators
Classifier: Programming Language :: Python :: 2.7
